dgh/__init__.py
dgh/constants.py
dgh/dgh.py
dgh/fw.py
dgh/mappings.py
dgh/spaces.py
dgh-0.2.0.dist-info/METADATA
dgh-0.2.0.dist-info/WHEEL
dgh-0.2.0.dist-info/licenses/LICENSE
dgh-0.2.0.dist-info/RECORD
