Metadata-Version: 2.4
Name: dgh
Version: 0.2.0
Summary: computing the Gromov–Hausdorff distance
Project-URL: Homepage, https://github.com/vlad-oles/dgh
Project-URL: Bug Tracker, https://github.com/vlad-oles/dgh/issues
Author-email: Vladyslav Oles <vlad.oles@proton.me>
License-File: LICENSE
Classifier: License :: OSI Approved :: MIT License
Classifier: Operating System :: OS Independent
Classifier: Programming Language :: Python :: 3
Requires-Python: >=3.5
Requires-Dist: numpy>=1.17.0
Provides-Extra: dev
Requires-Dist: pytest>=7.0; extra == 'dev'
Requires-Dist: scipy>=0.7.0; extra == 'dev'
